vinfo.py
vinfo-0.0.1.dist-info/METADATA
vinfo-0.0.1.dist-info/WHEEL
vinfo-0.0.1.dist-info/entry_points.txt
vinfo-0.0.1.dist-info/top_level.txt
vinfo-0.0.1.dist-info/RECORD
